ray_elasticsearch/__init__.py
ray_elasticsearch/_compat.py
ray_elasticsearch/_model.py
ray_elasticsearch/_schema.py
ray_elasticsearch/_sink.py
ray_elasticsearch/_source.py
ray_elasticsearch/_utils.py
ray_elasticsearch/test_schema.py
ray_elasticsearch/test_utils.py
ray_elasticsearch-1.1.4.dist-info/licenses/LICENSE
ray_elasticsearch-1.1.4.dist-info/METADATA
ray_elasticsearch-1.1.4.dist-info/WHEEL
ray_elasticsearch-1.1.4.dist-info/top_level.txt
ray_elasticsearch-1.1.4.dist-info/RECORD
