Metadata-Version: 2.4
Name: ray-elasticsearch
Version: 1.1.4
Summary: Ray data source and sink for Elasticsearch.
Author-email: Jan Heinrich Merker <heinrich.merker@uni-jena.de>
License-Expression: MIT
Project-URL: Homepage, https://github.com/janheinrichmerker/ray-elasticsearch
Project-URL: Bug Tracker, https://github.com/janheinrichmerker/ray-elasticsearch/issues
Classifier: Programming Language :: Python :: 3
Classifier: Programming Language :: Python :: 3 :: Only
Classifier: Programming Language :: Python :: 3.9
Classifier: Programming Language :: Python :: 3.10
Classifier: Programming Language :: Python :: 3.11
Classifier: Programming Language :: Python :: 3.12
Classifier: Programming Language :: Python :: 3.13
Classifier: Operating System :: OS Independent
Classifier: Intended Audience :: Science/Research
Classifier: Topic :: Scientific/Engineering
Requires-Python: >=3.9
License-File: LICENSE
Requires-Dist: elastic-transport<10,>=8
Requires-Dist: pyarrow<22,>=20
Requires-Dist: ray[data]~=2.49
Requires-Dist: typing-extensions~=4.15
Provides-Extra: tests
Requires-Dist: mypy~=1.6; extra == "tests"
Requires-Dist: pandas-stubs~=2.0; extra == "tests"
Requires-Dist: pyarrow-stubs~=20.0; extra == "tests"
Requires-Dist: pytest~=8.0; extra == "tests"
Requires-Dist: pytest-cov~=7.0; extra == "tests"
Requires-Dist: pyarrow-stubs<21,>=10; extra == "tests"
Requires-Dist: ruff~=0.13.0; extra == "tests"
Provides-Extra: tests-es7
Requires-Dist: elasticsearch~=7.0; extra == "tests-es7"
Provides-Extra: tests-es7-major
Requires-Dist: elasticsearch7~=7.0; extra == "tests-es7-major"
Provides-Extra: tests-es7-dsl
Requires-Dist: elasticsearch~=7.0; extra == "tests-es7-dsl"
Requires-Dist: elasticsearch-dsl~=7.0; extra == "tests-es7-dsl"
Provides-Extra: tests-es7-dsl-major
Requires-Dist: elasticsearch7~=7.0; extra == "tests-es7-dsl-major"
Requires-Dist: elasticsearch7-dsl~=7.0; extra == "tests-es7-dsl-major"
Provides-Extra: tests-es7-pydantic
Requires-Dist: elasticsearch~=7.0; extra == "tests-es7-pydantic"
Requires-Dist: elasticsearch-dsl~=7.0; extra == "tests-es7-pydantic"
Requires-Dist: elasticsearch-pydantic~=1.0; extra == "tests-es7-pydantic"
Provides-Extra: tests-es7-pydantic-major
Requires-Dist: elasticsearch7~=7.0; extra == "tests-es7-pydantic-major"
Requires-Dist: elasticsearch7-dsl~=7.0; extra == "tests-es7-pydantic-major"
Requires-Dist: elasticsearch-pydantic~=1.0; extra == "tests-es7-pydantic-major"
Provides-Extra: tests-es8
Requires-Dist: elasticsearch~=8.0; extra == "tests-es8"
Provides-Extra: tests-es8-major
Requires-Dist: elasticsearch8~=8.0; extra == "tests-es8-major"
Provides-Extra: tests-es8-dsl
Requires-Dist: elasticsearch~=8.0; extra == "tests-es8-dsl"
Requires-Dist: elasticsearch-dsl<8.12.0,~=8.0; extra == "tests-es8-dsl"
Provides-Extra: tests-es8-dsl-major
Requires-Dist: elasticsearch8~=8.0; extra == "tests-es8-dsl-major"
Requires-Dist: elasticsearch8-dsl<8.12.0,~=8.0; extra == "tests-es8-dsl-major"
Provides-Extra: tests-es8-pydantic
Requires-Dist: elasticsearch~=8.0; extra == "tests-es8-pydantic"
Requires-Dist: elasticsearch-dsl<8.12.0,~=8.0; extra == "tests-es8-pydantic"
Requires-Dist: elasticsearch-pydantic~=1.0; extra == "tests-es8-pydantic"
Provides-Extra: tests-es8-pydantic-major
Requires-Dist: elasticsearch8~=8.0; extra == "tests-es8-pydantic-major"
Requires-Dist: elasticsearch8-dsl<8.12.0,~=8.0; extra == "tests-es8-pydantic-major"
Requires-Dist: elasticsearch-pydantic~=1.0; extra == "tests-es8-pydantic-major"
Provides-Extra: examples
Requires-Dist: elasticsearch~=8.0; extra == "examples"
Requires-Dist: elasticsearch-dsl<8.12.0,~=8.0; extra == "examples"
Requires-Dist: ray[default]~=2.49; extra == "examples"
Dynamic: license-file
